vto_users/__init__.py
vto_users/admin.py
vto_users/apps.py
vto_users/models.py
vto_users/migrations/0001_initial.py
vto_users/migrations/__init__.py
vto_users-0.0.2.dist-info/METADATA
vto_users-0.0.2.dist-info/WHEEL
vto_users-0.0.2.dist-info/licenses/LICENSE
vto_users-0.0.2.dist-info/RECORD
