Metadata-Version: 2.4
Name: vto-users
Version: 0.0.2
Summary: This is a custom reusable Django users app.
Project-URL: Repository, https://github.com/venteto/vto-users
License-Expression: MIT
License-File: LICENSE
Requires-Python: >=3.13
